git_commit_gen/__init__.py
git_commit_gen/git_commit_gen.py
git_commit_gen-0.1.2.dist-info/METADATA
git_commit_gen-0.1.2.dist-info/WHEEL
git_commit_gen-0.1.2.dist-info/entry_points.txt
git_commit_gen-0.1.2.dist-info/licenses/LICENSE
git_commit_gen-0.1.2.dist-info/RECORD
