Metadata-Version: 2.4
Name: git-commit-gen
Version: 0.1.2
Summary: A tool to generate conventional commit messages using Gemini API
Project-URL: repository, https://github.com/salnika/git-commit-gen
Project-URL: homepage, https://github.com/salnika/git-commit-gen
License: Copyright (c) 2025
License-File: LICENSE
Requires-Python: >=3.8
Requires-Dist: google-generativeai>=0.5.0
Requires-Dist: pygit2>=1.12.0
Requires-Dist: python-dotenv>=1.0.0
